rnit_vanna/__init__.py
rnit_vanna/enhanced.py
rnit_vanna/utilities.py
rnit_vanna-2.0.0.dist-info/licenses/LICENSE
rnit_vanna-2.0.0.dist-info/METADATA
rnit_vanna-2.0.0.dist-info/WHEEL
rnit_vanna-2.0.0.dist-info/top_level.txt
rnit_vanna-2.0.0.dist-info/RECORD
