Metadata-Version: 2.4
Name: rnit-vanna
Version: 2.0.0
Summary: Enhanced wrapper for Vanna SQL generation library with custom utilities
Home-page: https://github.com/rnit/rnit-vanna
Author: RNIT
Author-email: RNIT <aryanrathore040@gmail.com>
License: MIT
Project-URL: Homepage, https://github.com/rnit/rnit-vanna
Project-URL: Documentation, https://github.com/rnit/rnit-vanna/wiki
Project-URL: Repository, https://github.com/rnit/rnit-vanna
Project-URL: Bug Tracker, https://github.com/rnit/rnit-vanna/issues
Keywords: sql,nlp,gpt,openai,database,query,natural-language,vanna,ai
Classifier: Development Status :: 4 - Beta
Classifier: Intended Audience :: Developers
Classifier: Topic :: Software Development :: Libraries :: Python Modules
Classifier: Topic :: Database
Classifier: Topic :: Scientific/Engineering :: Artificial Intelligence
Classifier: Programming Language :: Python :: 3
Classifier: Programming Language :: Python :: 3.7
Classifier: Programming Language :: Python :: 3.8
Classifier: Programming Language :: Python :: 3.9
Classifier: Programming Language :: Python :: 3.10
Classifier: Programming Language :: Python :: 3.11
Classifier: License :: OSI Approved :: MIT License
Classifier: Operating System :: OS Independent
Requires-Python: >=3.7
License-File: LICENSE
Requires-Dist: vanna[chromadb,openai]>=0.5.0
Requires-Dist: python-dotenv>=0.19.0
Provides-Extra: dev
Requires-Dist: pytest>=7.0.0; extra == "dev"
Requires-Dist: black>=22.0.0; extra == "dev"
Requires-Dist: flake8>=4.0.0; extra == "dev"
Provides-Extra: postgres
Requires-Dist: psycopg2-binary>=2.9.0; extra == "postgres"
Provides-Extra: mysql
Requires-Dist: pymysql>=1.0.0; extra == "mysql"
Dynamic: author
Dynamic: home-page
Dynamic: license-file
Dynamic: requires-python
